pepe_toolbox/__init__.py
pepe_toolbox/File/__init__.py
pepe_toolbox/File/document_preprocessor.py
pepe_toolbox/File/file_manager.py
pepe_toolbox/File/image_converter.py
pepe_toolbox/Slack/__init__.py
pepe_toolbox/Slack/slack_pepe.py
pepe_toolbox-0.3.7.dist-info/LICENSE
pepe_toolbox-0.3.7.dist-info/METADATA
pepe_toolbox-0.3.7.dist-info/WHEEL
pepe_toolbox-0.3.7.dist-info/top_level.txt
pepe_toolbox-0.3.7.dist-info/RECORD
