Metadata-Version: 2.1
Name: pepe-toolbox
Version: 0.3.7
Summary: korean pepe lover
Home-page: https://github.com/kinest1997
Author: kinest1997
Author-email: kinest1997@naver.com
Classifier: Programming Language :: Python :: 3
Classifier: License :: OSI Approved :: MIT License
Classifier: Operating System :: OS Independent
Requires-Python: >=3.6
License-File: LICENSE
Requires-Dist: requests ==2.32.3
Requires-Dist: slack-sdk ==3.32.0
Requires-Dist: Pillow
Requires-Dist: pdf2image
Requires-Dist: tqdm
